normatrix/__init__.py
normatrix/__main__.py
normatrix/plugged/__init__.py
normatrix/plugged/columns.py
normatrix/plugged/comma.py
normatrix/plugged/comments.py
normatrix/plugged/function_line.py
normatrix/plugged/header.py
normatrix/plugged/indent.py
normatrix/plugged/libc_func.py
normatrix/plugged/nb_params.py
normatrix/plugged/nested_branches.py
normatrix/plugged/newline_at_end_of_file.py
normatrix/plugged/number_function.py
normatrix/plugged/operators.py
normatrix/plugged/parenthesis.py
normatrix/plugged/preprocessor.py
normatrix/plugged/snake_case.py
normatrix/plugged/solo_space.py
normatrix/plugged/statements.py
normatrix/plugged/subscriptor.py
normatrix/plugged/trailing_newline.py
normatrix/plugged/two_space.py
normatrix/source/__init__.py
normatrix/source/call_plugged.py
normatrix/source/color.py
normatrix/source/config.py
normatrix/source/context.py
normatrix/source/custom_regex.py
normatrix/source/file_parser.py
normatrix/source/get_file_to_check.py
normatrix/source/main.py
normatrix/source/makefile.py
normatrix/source/print_right_format.py
normatrix/source/print_stats.py
normatrix/test/tests.py
normatrix/test/unittests/columns/tests.py
normatrix/test/unittests/comma/tests.py
normatrix/test/unittests/function_line/tests.py
normatrix/test/unittests/header/tests.py
normatrix/test/unittests/indent/tests.py
normatrix/test/unittests/libc_func/tests.py
normatrix/test/unittests/nb_params/tests.py
normatrix/test/unittests/nested_branches/tests.py
normatrix/test/unittests/newline_at_end_of_file/tests.py
normatrix/test/unittests/number_function/tests.py
normatrix/test/unittests/operators/tests.py
normatrix/test/unittests/parenthesis/tests.py
normatrix/test/unittests/preprocessor/tests.py
normatrix/test/unittests/snake_case/tests.py
normatrix/test/unittests/solo_space/tests.py
normatrix/test/unittests/statements/tests.py
normatrix/test/unittests/subscriptor/tests.py
normatrix/test/unittests/trailing_newline/tests.py
normatrix/test/unittests/two_space/tests.py
normatrix-0.4.0.dist-info/LICENSE
normatrix-0.4.0.dist-info/METADATA
normatrix-0.4.0.dist-info/WHEEL
normatrix-0.4.0.dist-info/top_level.txt
normatrix-0.4.0.dist-info/RECORD
