Metadata-Version: 2.1
Name: normatrix
Version: 0.4.0
Summary: check epitech c coding style
Home-page: https://github.com/Saverio976/NorMatrix
Author: Saverio
Author-email: Saverio <personnex976@gmail.com>
License: MIT
Project-URL: Bug Tracker, https://github.com/Saverio976/NorMatrix/issues/new/choose
Project-URL: Example Workflow, https://github.com/Saverio976/NorMatrix/actions/workflows/normatrix_check.yml
Keywords: epitech,coding style,c,normatrix
Classifier: Programming Language :: Python :: 3
Classifier: License :: OSI Approved :: MIT License
Classifier: Operating System :: OS Independent
Classifier: Environment :: Console
Classifier: Programming Language :: C
Classifier: Topic :: Software Development :: Quality Assurance
Requires-Python: >=3.7
License-File: LICENSE
Requires-Dist: markdown
Requires-Dist: regex
Requires-Dist: rich
